[
    {
        "X": "AP",
        "Y": 0.0
    },
    {
        "X": "AA",
        "Y": 4.244817374
    },
    {
        "X": "AB",
        "Y": 4.047384008
    },
    {
        "X": "BB",
        "Y": 5.231984205
    },
    {
        "X": "BC",
        "Y": 5.034550839
    },
    {
        "X": "CC",
        "Y": 2.764067127
    },
    {
        "X": "CD",
        "Y": 2.369200395
    },
    {
        "X": "DD",
        "Y": 1.184600197
    },
    {
        "X": "FR",
        "Y": 0.296150049
    }
]